LICENSE
MANIFEST.in
README.rst
setup.py
upload.bat
radware_os_lb_v2_liberty/__init__.py
radware_os_lb_v2_liberty/base_v2_driver.py
radware_os_lb_v2_liberty/exceptions.py
radware_os_lb_v2_liberty/my_driver.py
radware_os_lb_v2_liberty/rest_client.py
radware_os_lb_v2_liberty/v2_driver.py
radware_os_lb_v2_liberty.egg-info/PKG-INFO
radware_os_lb_v2_liberty.egg-info/SOURCES.txt
radware_os_lb_v2_liberty.egg-info/dependency_links.txt
radware_os_lb_v2_liberty.egg-info/not-zip-safe
radware_os_lb_v2_liberty.egg-info/top_level.txt